CreditScoreModel/LogisticScoreCard.py
CreditScoreModel/__init__.py
CreditScoreModel-2.0.5.dist-info/DESCRIPTION.rst
CreditScoreModel-2.0.5.dist-info/METADATA
CreditScoreModel-2.0.5.dist-info/RECORD
CreditScoreModel-2.0.5.dist-info/WHEEL
CreditScoreModel-2.0.5.dist-info/metadata.json
CreditScoreModel-2.0.5.dist-info/top_level.txt
